amazon_chat_completions_server/__init__.py
amazon_chat_completions_server/main.py
amazon_chat_completions_server/version.py
amazon_chat_completions_server/adapters/__init__.py
amazon_chat_completions_server/adapters/base_adapter.py
amazon_chat_completions_server/adapters/bedrock_to_openai_adapter.py
amazon_chat_completions_server/adapters/openai_adapter.py
amazon_chat_completions_server/adapters/bedrock/__init__.py
amazon_chat_completions_server/adapters/bedrock/ai21_strategy.py
amazon_chat_completions_server/adapters/bedrock/bedrock_adapter.py
amazon_chat_completions_server/adapters/bedrock/bedrock_adapter_strategy_abc.py
amazon_chat_completions_server/adapters/bedrock/bedrock_models.py
amazon_chat_completions_server/adapters/bedrock/claude_strategy.py
amazon_chat_completions_server/adapters/bedrock/cohere_strategy.py
amazon_chat_completions_server/adapters/bedrock/meta_strategy.py
amazon_chat_completions_server/adapters/bedrock/mistral_strategy.py
amazon_chat_completions_server/adapters/bedrock/nova_strategy.py
amazon_chat_completions_server/adapters/bedrock/stability_strategy.py
amazon_chat_completions_server/adapters/bedrock/titan_strategy.py
amazon_chat_completions_server/adapters/bedrock/writer_strategy.py
amazon_chat_completions_server/api/__init__.py
amazon_chat_completions_server/api/app.py
amazon_chat_completions_server/api/errors.py
amazon_chat_completions_server/api/dependencies/__init__.py
amazon_chat_completions_server/api/dependencies/services.py
amazon_chat_completions_server/api/middleware/__init__.py
amazon_chat_completions_server/api/middleware/auth.py
amazon_chat_completions_server/api/middleware/logging.py
amazon_chat_completions_server/api/routes/__init__.py
amazon_chat_completions_server/api/routes/chat.py
amazon_chat_completions_server/api/routes/health.py
amazon_chat_completions_server/api/routes/models.py
amazon_chat_completions_server/api/schemas/__init__.py
amazon_chat_completions_server/api/schemas/requests.py
amazon_chat_completions_server-1.0.0.dist-info/licenses/LICENSE
amazon_chat_completions_server-1.0.0.dist-info/METADATA
amazon_chat_completions_server-1.0.0.dist-info/WHEEL
amazon_chat_completions_server-1.0.0.dist-info/entry_points.txt
amazon_chat_completions_server-1.0.0.dist-info/top_level.txt
amazon_chat_completions_server-1.0.0.dist-info/RECORD
